LICENSE
README.md
setup.py
argsdict/__init__.py
argsdict/argsdict.py
argsdict.egg-info/PKG-INFO
argsdict.egg-info/SOURCES.txt
argsdict.egg-info/dependency_links.txt
argsdict.egg-info/top_level.txt