Metadata-Version: 2.1
Name: argsdict
Version: 1.0.0
Summary: Simple command-line argument parser.
Home-page: https://github.com/Julynx/argsdict
Author: Julio Cabria
Author-email: juliocabria@tutanota.com
Maintainer: Julio Cabria
Maintainer-email: juliocabria@tutanota.com
License: GPLv2
License-File: LICENSE
